cell_AAP/__init__.py
cell_AAP/configs.py
cell_AAP/defaults.py
cell_AAP/napari.yaml
cell_AAP/annotation/__init__.py
cell_AAP/annotation/annotation_utils.py
cell_AAP/annotation/annotator.py
cell_AAP/annotation/dataset_convert.py
cell_AAP/annotation/dataset_write.py
cell_AAP/annotation/pycococreator/__init__.py
cell_AAP/annotation/pycococreator/pycococreatortools/__init__.py
cell_AAP/annotation/pycococreator/pycococreatortools/pycococreatortools.py
cell_AAP/core/__init__.py
cell_AAP/core/inference_core.py
cell_AAP/napari/__init__.py
cell_AAP/napari/fileio.py
cell_AAP/napari/main.py
cell_AAP/napari/sub_widgets.py
cell_AAP/napari/ui.py
cell_AAP/napari_dataset/__init__.py
cell_AAP/napari_dataset/combined.py
cell_AAP/napari_dataset/config_editor.py
cell_AAP/napari_dataset/fileio.py
cell_AAP/napari_dataset/main.py
cell_AAP/napari_dataset/napari.yaml
cell_AAP/napari_dataset/results_viewer.py
cell_AAP/napari_dataset/simple_coco_convert.py
cell_AAP/napari_dataset/ui.py
cell_AAP/napari_dataset/zenodo_uploader.py
cell_AAP/scripts/batch_inference.py
cell_AAP/scripts/inference.py
cell_AAP/scripts/run_inference.py
cell_aap-1.0.7.dist-info/licenses/LICENSE
cell_aap-1.0.7.dist-info/METADATA
cell_aap-1.0.7.dist-info/WHEEL
cell_aap-1.0.7.dist-info/entry_points.txt
cell_aap-1.0.7.dist-info/top_level.txt
cell_aap-1.0.7.dist-info/RECORD
