Metadata-Version: 2.4
Name: cell-AAP
Version: 1.0.7
Author: Anish Virdi
License: MIT
Classifier: Framework :: napari
Classifier: Programming Language :: Python :: 3
Requires-Python: <3.13,>=3.11
License-File: LICENSE
Requires-Dist: napari[all]>=0.4.19
Requires-Dist: numpy<2.0,>=1.23
Requires-Dist: opencv-python>=4.9.0
Requires-Dist: tifffile>=2024.2.12
Requires-Dist: scikit-image<0.26.0,>=0.23.2
Requires-Dist: qtpy>=2.4.1
Requires-Dist: pillow>=10.3.0
Requires-Dist: scipy>=1.12.0
Requires-Dist: timm>=1.0.7
Requires-Dist: pandas>=2.2.2
Requires-Dist: superqt>=0.6.3
Requires-Dist: btrack>=0.6.5
Requires-Dist: seaborn>=0.13.2
Requires-Dist: openpyxl>=3.1.4
Requires-Dist: joblib>=1.0
Requires-Dist: scikit-learn>=0.22
Requires-Dist: segment-anything>=1.0
Requires-Dist: pycocotools>=2.0.7
Requires-Dist: lxml>=4.9.0
Requires-Dist: lxml_html_clean>=0.1.0
Requires-Dist: shapely<=2.0.4
Requires-Dist: ruamel.yaml<=0.19.1
Provides-Extra: torch
Requires-Dist: torch>=2.3.1; platform_system != "Darwin" and extra == "torch"
Requires-Dist: torchvision>=0.18.1; platform_system != "Darwin" and extra == "torch"
Provides-Extra: torch-macos
Provides-Extra: full
Requires-Dist: torch>=2.3.1; platform_system != "Darwin" and extra == "full"
Requires-Dist: torchvision>=0.18.1; platform_system != "Darwin" and extra == "full"
Dynamic: license-file
